LICENSE
README.md
setup.cfg
setup.py
VisionCraftAPI/__init__.py
VisionCraftAPI/api.py
VisionCraftAPI/http_client.py
VisionCraftAPI.egg-info/PKG-INFO
VisionCraftAPI.egg-info/SOURCES.txt
VisionCraftAPI.egg-info/dependency_links.txt
VisionCraftAPI.egg-info/not-zip-safe
VisionCraftAPI.egg-info/requires.txt
VisionCraftAPI.egg-info/top_level.txt
VisionCraftAPI/enums/__init__.py
VisionCraftAPI/enums/modes.py
VisionCraftAPI/enums/task_statuses.py
VisionCraftAPI/exceptions/__init__.py
VisionCraftAPI/exceptions/types.py
VisionCraftAPI/models/__init__.py
VisionCraftAPI/models/limits.py
VisionCraftAPI/models/llm.py
VisionCraftAPI/models/midjourney.py
VisionCraftAPI/models/whisper.py
VisionCraftAPI/utils/__init__.py
VisionCraftAPI/utils/checker.py