Metadata-Version: 2.1
Name: VisionCraftAPI
Version: 1.0.3
Summary: Fully async python wrapper for VisionCraft API
Home-page: https://github.com/Belyashik2K/VisionCraftAPI
Author: Belyashik2K
Author-email: work@belyashik2k.ru
License: MIT license
License-File: LICENSE
